pygambit/__init__.py
pygambit/action.pxi
pygambit/behavmixed.pxi
pygambit/enumeration.py
pygambit/error.py
pygambit/gambit.cp310-win_amd64.pyd
pygambit/gambit.cpp
pygambit/gambit.pxd
pygambit/gambit.pyx
pygambit/game.pxi
pygambit/gameiter.py
pygambit/infoset.pxi
pygambit/levelk.py
pygambit/nash.h
pygambit/nash.pxi
pygambit/nash.py
pygambit/nashlrs.py
pygambit/nashphc.py
pygambit/node.pxi
pygambit/outcome.pxi
pygambit/player.pxi
pygambit/profiles.py
pygambit/qre.py
pygambit/strategy.pxi
pygambit/stratmixed.pxi
pygambit/stratspt.pxi
pygambit/supports.py
pygambit/util.h
pygambit/util.py
pygambit-16.5.0.dist-info/licenses/AUTHORS
pygambit-16.5.0.dist-info/licenses/COPYING
pygambit-16.5.0.dist-info/licenses/license.rtf
pygambit-16.5.0.dist-info/METADATA
pygambit-16.5.0.dist-info/WHEEL
pygambit-16.5.0.dist-info/top_level.txt
pygambit-16.5.0.dist-info/RECORD
